jsontoqt/__init__.py
jsontoqt/__main__.py
jsontoqt/form.py
jsontoqt-0.4.1.dist-info/METADATA
jsontoqt-0.4.1.dist-info/WHEEL
jsontoqt-0.4.1.dist-info/top_level.txt
jsontoqt-0.4.1.dist-info/RECORD
