Metadata-Version: 2.4
Name: jsontoqt
Version: 0.4.1
Summary: Convert JSON schemas into dynamic PySide6 GUI forms with no manual UI coding needed.
Author-email: JupiterDev <thatgeometrydude@gmail.com>
License: MIT
Project-URL: Homepage, https://github.com/thejupiterdev/jsontoqt
Project-URL: Repository, https://github.com/thejupiterdev/jsontoqt
Keywords: PySide6,Qt,JSON,GUI,forms
Classifier: Programming Language :: Python :: 3
Classifier: License :: OSI Approved :: MIT License
Classifier: Operating System :: OS Independent
Requires-Python: >=3.8
